{
    "asset": {
        "format": "png",
        "id": "3992bed164fcc14192ce096be80b72db",
        "name": "out43.png",
        "path": "file:C:/Users/Justin%20McGowen/Documents/CompVis/images/out43.png",
        "size": {
            "width": 1920,
            "height": 1080
        },
        "state": 2,
        "type": 1
    },
    "regions": [
        {
            "id": "UXVGg4MTT",
            "type": "RECTANGLE",
            "tags": [
                "Enemy"
            ],
            "boundingBox": {
                "height": 95.51020408163265,
                "width": 37.64705882352941,
                "left": 894.3472022955524,
                "top": 399.5758928571429
            },
            "points": [
                {
                    "x": 894.3472022955524,
                    "y": 399.5758928571429
                },
                {
                    "x": 931.9942611190818,
                    "y": 399.5758928571429
                },
                {
                    "x": 931.9942611190818,
                    "y": 495.08609693877554
                },
                {
                    "x": 894.3472022955524,
                    "y": 495.08609693877554
                }
            ]
        },
        {
            "id": "e2hFbw1NZ",
            "type": "RECTANGLE",
            "tags": [
                "Enemy"
            ],
            "boundingBox": {
                "height": 123.06122448979592,
                "width": 54.175035868005736,
                "left": 907.2022955523673,
                "top": 410.5963010204082
            },
            "points": [
                {
                    "x": 907.2022955523673,
                    "y": 410.5963010204082
                },
                {
                    "x": 961.377331420373,
                    "y": 410.5963010204082
                },
                {
                    "x": 961.377331420373,
                    "y": 533.6575255102041
                },
                {
                    "x": 907.2022955523673,
                    "y": 533.6575255102041
                }
            ]
        },
        {
            "id": "pHgoe3-qT",
            "type": "RECTANGLE",
            "tags": [
                "Friendly"
            ],
            "boundingBox": {
                "height": 52.3469387755102,
                "width": 29.383070301291248,
                "left": 794.261119081779,
                "top": 435.3922193877551
            },
            "points": [
                {
                    "x": 794.261119081779,
                    "y": 435.3922193877551
                },
                {
                    "x": 823.6441893830703,
                    "y": 435.3922193877551
                },
                {
                    "x": 823.6441893830703,
                    "y": 487.7391581632653
                },
                {
                    "x": 794.261119081779,
                    "y": 487.7391581632653
                }
            ]
        },
        {
            "id": "7lq9IYeIi",
            "type": "RECTANGLE",
            "tags": [
                "Friendly"
            ],
            "boundingBox": {
                "height": 583.077168367347,
                "width": 673.974175035868,
                "left": 0,
                "top": 496.9228316326531
            },
            "points": [
                {
                    "x": 0,
                    "y": 496.9228316326531
                },
                {
                    "x": 673.974175035868,
                    "y": 496.9228316326531
                },
                {
                    "x": 673.974175035868,
                    "y": 1080
                },
                {
                    "x": 0,
                    "y": 1080
                }
            ]
        }
    ],
    "version": "2.1.0"
}