{
    "asset": {
        "format": "png",
        "id": "439b65a120accfbf05bfb019c402333e",
        "name": "out746.png",
        "path": "file:C:/Users/Justin%20McGowen/Documents/CompVis/images/out746.png",
        "size": {
            "width": 1920,
            "height": 1080
        },
        "state": 2,
        "type": 1
    },
    "regions": [
        {
            "id": "xFXahWusG",
            "type": "RECTANGLE",
            "tags": [
                "Enemy"
            ],
            "boundingBox": {
                "height": 63.36734693877551,
                "width": 26.628407460545194,
                "left": 956.7862266857962,
                "top": 520.8003826530612
            },
            "points": [
                {
                    "x": 956.7862266857962,
                    "y": 520.8003826530612
                },
                {
                    "x": 983.4146341463414,
                    "y": 520.8003826530612
                },
                {
                    "x": 983.4146341463414,
                    "y": 584.1677295918367
                },
                {
                    "x": 956.7862266857962,
                    "y": 584.1677295918367
                }
            ]
        },
        {
            "id": "t1n_7VsHz",
            "type": "RECTANGLE",
            "tags": [
                "Friendly"
            ],
            "boundingBox": {
                "height": 112.9591836734694,
                "width": 57.84791965566714,
                "left": 894.3472022955524,
                "top": 512.5350765306123
            },
            "points": [
                {
                    "x": 894.3472022955524,
                    "y": 512.5350765306123
                },
                {
                    "x": 952.1951219512194,
                    "y": 512.5350765306123
                },
                {
                    "x": 952.1951219512194,
                    "y": 625.4942602040817
                },
                {
                    "x": 894.3472022955524,
                    "y": 625.4942602040817
                }
            ]
        }
    ],
    "version": "2.1.0"
}