{
    "asset": {
        "format": "png",
        "id": "f152f16d5cd0e50f92e6e1af67a823b6",
        "name": "out358.png",
        "path": "file:C:/Users/Justin%20McGowen/Documents/CompVis/images/out358.png",
        "size": {
            "width": 1920,
            "height": 1080
        },
        "state": 2,
        "type": 1
    },
    "regions": [
        {
            "id": "kmMIhgMHt",
            "type": "RECTANGLE",
            "tags": [
                "Friendly"
            ],
            "boundingBox": {
                "height": 27.551020408163264,
                "width": 23.87374461979914,
                "left": 834.6628407460545,
                "top": 458.3514030612245
            },
            "points": [
                {
                    "x": 834.6628407460545,
                    "y": 458.3514030612245
                },
                {
                    "x": 858.5365853658536,
                    "y": 458.3514030612245
                },
                {
                    "x": 858.5365853658536,
                    "y": 485.90242346938777
                },
                {
                    "x": 834.6628407460545,
                    "y": 485.90242346938777
                }
            ]
        },
        {
            "id": "fCViPdNHE",
            "type": "RECTANGLE",
            "tags": [
                "EnemyWithNameOverlay"
            ],
            "boundingBox": {
                "height": 191.0204081632653,
                "width": 99.16786226685797,
                "left": 929.2395982783357,
                "top": 513.4534438775511
            },
            "points": [
                {
                    "x": 929.2395982783357,
                    "y": 513.4534438775511
                },
                {
                    "x": 1028.4074605451938,
                    "y": 513.4534438775511
                },
                {
                    "x": 1028.4074605451938,
                    "y": 704.4738520408164
                },
                {
                    "x": 929.2395982783357,
                    "y": 704.4738520408164
                }
            ]
        },
        {
            "id": "9d3gyaMZ7",
            "type": "RECTANGLE",
            "tags": [
                "Enemy"
            ],
            "boundingBox": {
                "height": 364.5918367346939,
                "width": 196.49928263988522,
                "left": 1159.713055954089,
                "top": 485.90242346938777
            },
            "points": [
                {
                    "x": 1159.713055954089,
                    "y": 485.90242346938777
                },
                {
                    "x": 1356.2123385939742,
                    "y": 485.90242346938777
                },
                {
                    "x": 1356.2123385939742,
                    "y": 850.4942602040817
                },
                {
                    "x": 1159.713055954089,
                    "y": 850.4942602040817
                }
            ]
        }
    ],
    "version": "2.1.0"
}